{
  "routes": [
    {
      "method": "GET",
      "path": "/npcs",
      "handler": "npc.find",
      "config": {
        "policies": []
      }
    },
    {
      "method": "GET",
      "path": "/npcs/count",
      "handler": "npc.count",
      "config": {
        "policies": []
      }
    },
    {
      "method": "GET",
      "path": "/npcs/:id",
      "handler": "npc.findOne",
      "config": {
        "policies": []
      }
    },
    {
      "method": "POST",
      "path": "/npcs",
      "handler": "npc.create",
      "config": {
        "policies": []
      }
    },
    {
      "method": "PUT",
      "path": "/npcs/:id",
      "handler": "npc.update",
      "config": {
        "policies": []
      }
    },
    {
      "method": "DELETE",
      "path": "/npcs/:id",
      "handler": "npc.delete",
      "config": {
        "policies": []
      }
    }
  ]
}
